uniphy/__init__.py
uniphy/decorators.py
uniphy-0.0.3.dist-info/DESCRIPTION.rst
uniphy-0.0.3.dist-info/METADATA
uniphy-0.0.3.dist-info/RECORD
uniphy-0.0.3.dist-info/WHEEL
uniphy-0.0.3.dist-info/metadata.json
uniphy-0.0.3.dist-info/top_level.txt
